Metadata-Version: 1.0
Name: bqlint
Version: 0.0.4
Summary: A linter for BigQuery's Standard SQL
Home-page: https://github.com/TKNGUE/bqlint
Author: TKNGUE
Author-email: UNKNOWN
License: MIT
Platform: UNKNOWN
